ml_investment/__init__.py
ml_investment/download.py
ml_investment/features.py
ml_investment/metrics.py
ml_investment/models.py
ml_investment/pipelines.py
ml_investment/targets.py
ml_investment/utils.py
ml_investment/applications/__init__.py
ml_investment/applications/fair_marketcap_diff_sf1.py
ml_investment/applications/fair_marketcap_diff_sf1_v2.py
ml_investment/applications/fair_marketcap_diff_yahoo.py
ml_investment/applications/fair_marketcap_sf1.py
ml_investment/applications/fair_marketcap_sf1_v2.py
ml_investment/applications/fair_marketcap_yahoo.py
ml_investment/applications/marketcap_down_std_sf1.py
ml_investment/applications/marketcap_down_std_yahoo.py
ml_investment/backtest/__init__.py
ml_investment/backtest/strategy.py
ml_investment/data_loaders/__init__.py
ml_investment/data_loaders/daily_bars.py
ml_investment/data_loaders/mongo.py
ml_investment/data_loaders/news.py
ml_investment/data_loaders/quandl_commodities.py
ml_investment/data_loaders/sf1.py
ml_investment/data_loaders/yahoo.py
ml_investment/download_scripts/__init__.py
ml_investment/download_scripts/download_commodities.py
ml_investment/download_scripts/download_daily_bars.py
ml_investment/download_scripts/download_sf1.py
ml_investment/download_scripts/download_yahoo.py
ml_investment/download_scripts/download_yahoo_v1.py
ml_investment/download_scripts/download_yahoo_v2.py
ml_investment-0.0.25.dist-info/METADATA
ml_investment-0.0.25.dist-info/WHEEL
ml_investment-0.0.25.dist-info/top_level.txt
ml_investment-0.0.25.dist-info/RECORD
