Metadata-Version: 2.1
Name: ml-investment
Version: 0.0.25
Summary: Machine learning tools for investment
Home-page: https://github.com/fartuk/ml_investment
Author: Artur Fattakhov
Author-email: fao3864@gmail.com
License: UNKNOWN
Project-URL: Bug Tracker, https://github.com/fartuk/ml_investment/issues
Platform: UNKNOWN
Classifier: Programming Language :: Python :: 3
Classifier: License :: OSI Approved :: MIT License
Classifier: Operating System :: OS Independent
Requires-Python: >=3.6.0
Requires-Dist: numpy (>=1.21.4)
Requires-Dist: pandas (>=1.1.0)
Requires-Dist: lightgbm (>=2.3.1)
Requires-Dist: catboost (>=0.24.4)
Requires-Dist: tqdm (>=4.46.1)
Requires-Dist: requests (>=2.23.0)
Requires-Dist: pytest (>=6.2.2)
Requires-Dist: pandas-datareader (>=0.10.0)
Requires-Dist: pymongo (==3.11.4)
